strbalance/__init__.py
strbalance/balance.py
strbalance/strbalance.py
strbalance/unbalanced.py
strbalance-0.3.1.dist-info/METADATA
strbalance-0.3.1.dist-info/RECORD
strbalance-0.3.1.dist-info/WHEEL
strbalance-0.3.1.dist-info/top_level.txt
