Metadata-Version: 2.1
Name: strbalance
Version: 0.3.1
Summary: A package to check whether a string is balanced
Home-page: https://github.com/tamila-krashtan/strbalance
Author: Tamila Krashtan
Author-email: tamila.krashtan@gmail.com
License: UNKNOWN
Platform: UNKNOWN
Classifier: Programming Language :: Python :: 3
Classifier: License :: OSI Approved :: MIT License
Requires-Python: >=3
